dicomsync/__init__.py
dicomsync/core.py
dicomsync/exceptions.py
dicomsync/filesystem.py
dicomsync/logs.py
dicomsync/persistence.py
dicomsync/references.py
dicomsync/routing.py
dicomsync/strings.py
dicomsync/ui.py
dicomsync/xnat.py
dicomsync/cli/__init__.py
dicomsync/cli/base.py
dicomsync/cli/click_parameter_types.py
dicomsync/cli/compare.py
dicomsync/cli/entrypoint.py
dicomsync/cli/find.py
dicomsync/cli/place.py
dicomsync/cli/send.py
dicomsync-1.3.0.dist-info/METADATA
dicomsync-1.3.0.dist-info/WHEEL
dicomsync-1.3.0.dist-info/entry_points.txt
dicomsync-1.3.0.dist-info/licenses/LICENSE
dicomsync-1.3.0.dist-info/RECORD
