Metadata-Version: 2.4
Name: dicomsync
Version: 1.3.0
Summary: Synchronize medical imaging studies between storage modalities
Author-email: sjoerdk <sjoerd.kerkstra@radboudumc.nl>
License-Expression: Apache-2.0
License-File: LICENSE
Classifier: Development Status :: 4 - Beta
Classifier: Intended Audience :: Developers
Classifier: Programming Language :: Python :: 3.10
Classifier: Programming Language :: Python :: 3.11
Classifier: Programming Language :: Python :: 3.12
Requires-Python: ~=3.10
Requires-Dist: coloredlogs<16,>=15.0.1
Requires-Dist: jinja2<4,>=3.1.6
Requires-Dist: pydantic>=2.12.3
Requires-Dist: python-slugify<9,>=8.0.4
Requires-Dist: setuptools>=80.9.0
Requires-Dist: tabulate<0.10,>=0.9.0
Requires-Dist: xnat>=0.7.2
